README.md
setup.py
conf/__init__.py
conf/config.py
dingding_client/__init__.py
dingding_client/client.py
lib/__init__.py
lib/func_ext.py
lib/log.py
lib/notice_client.py
lib/pyamqp.py
shopex_dingding_notify.egg-info/PKG-INFO
shopex_dingding_notify.egg-info/SOURCES.txt
shopex_dingding_notify.egg-info/dependency_links.txt
shopex_dingding_notify.egg-info/top_level.txt
test/SendMessageToDingDingTestCase.py
test/SendMessageToMqTestCase.py
test/__init__.py