Metadata-Version: 1.2
Name: shopex-dingding-notify
Version: 2.2
Summary: ShopEx dingding notify for python
Home-page: https://github.com/magic119/shopex_dingding_notify.git
Author: ShopEx
Author-email: xuhongtao@shopex.cn
License: LGPL
Platform: README.md
Requires-Python: >=3.6
